docgen/__init__.py
docgen/cli.py
docgen/analyzers/__init__.py
docgen/analyzers/base_analyzer.py
docgen/analyzers/code_analyzer.py
docgen/auth/__init__.py
docgen/auth/api_key_manager.py
docgen/auth/usage_tracker.py
docgen/config/__init__.py
docgen/config/config_handler.py
docgen/config/language_config.py
docgen/config/urls.py
docgen/generators/__init__.py
docgen/generators/ai_doc_generator.py
docgen/generators/docstring_generator.py
docgen/generators/markdown_generator.py
docgen/utils/__init__.py
docgen/utils/_machine_utils.cpp
docgen/utils/_machine_utils.cpython-39-darwin.so
docgen/utils/_machine_utils.pyx
docgen/utils/_machine_utils_py.py
docgen/utils/ai_client.py
docgen/utils/config.py
docgen/utils/extension.py
docgen/utils/git_utils.py
docgen/utils/machine_utils.py
docgen_cli-1.0.9.dist-info/LICENSE
docgen_cli-1.0.9.dist-info/METADATA
docgen_cli-1.0.9.dist-info/WHEEL
docgen_cli-1.0.9.dist-info/entry_points.txt
docgen_cli-1.0.9.dist-info/top_level.txt
docgen_cli-1.0.9.dist-info/RECORD
