Metadata-Version: 2.1
Name: docgen-cli
Version: 1.0.9
Summary: AI-Powered Documentation Generator for Developers
Home-page: https://github.com/aniket-0-cyber/docgen-cli
Author: Aniket Singh, Varshith
Author-email: aniket0999@gmail.com
License: UNKNOWN
Project-URL: Bug Reports, https://github.com/aniket-0-cyber/docgen-cli/issues
Project-URL: Source, https://github.com/aniket-0-cyber/docgen-cli
Keywords: documentation generator ai development tools docstring markdown
Platform: UNKNOWN
Classifier: Development Status :: 4 - Beta
Classifier: Intended Audience :: Developers
Classifier: Topic :: Software Development :: Documentation
Classifier: Programming Language :: Python :: 3
Classifier: Programming Language :: Python :: 3.8
Classifier: Programming Language :: Python :: 3.9
Classifier: Programming Language :: Python :: 3.10
Classifier: License :: OSI Approved :: MIT License
Classifier: Operating System :: OS Independent
Classifier: Environment :: Console
Classifier: Topic :: Documentation
Classifier: Topic :: Software Development :: Documentation
Classifier: Topic :: Software Development :: Libraries :: Python Modules
Requires-Python: >=3.7
License-File: LICENSE
Requires-Dist: aiohttp>=3.8.0
Requires-Dist: google-generativeai>=0.8.0
Requires-Dist: google-api-python-client>=2.100.0
Requires-Dist: google-auth>=2.22.0
Requires-Dist: typer>=0.9.0
Requires-Dist: rich>=13.3.0
Requires-Dist: gitpython>=3.1.30
Requires-Dist: esprima>=4.0.0
Requires-Dist: javalang>=0.13.0
Requires-Dist: python-dotenv>=1.0.0
Requires-Dist: requests>=2.28.0
Requires-Dist: tqdm>=4.65.0
Requires-Dist: cython>=3.0.0
Requires-Dist: pydantic>=2.0.0
Requires-Dist: ratelimit>=2.2.0
Requires-Dist: cryptography>=38.0.0
Requires-Dist: python-dotenv>=1.0.1
Requires-Dist: pywin32; platform_system == "Windows"
Provides-Extra: dev
Requires-Dist: pytest>=8.3.4; extra == "dev"
Requires-Dist: black>=24.10.0; extra == "dev"
Requires-Dist: isort>=5.13.2; extra == "dev"
Requires-Dist: mypy>=1.8.0; extra == "dev"
Requires-Dist: pytest-cov>=4.1.0; extra == "dev"
Requires-Dist: pytest-asyncio>=0.23.0; extra == "dev"
